lonelypsp/compat.py
lonelypsp/py.typed
lonelypsp/sync_io.py
lonelypsp/auth/config.py
lonelypsp/auth/set_subscriptions_info.py
lonelypsp/auth/helpers/hmac_auth_config.py
lonelypsp/auth/helpers/none_auth_config.py
lonelypsp/auth/helpers/token_auth_config.py
lonelypsp/stateful/constants.py
lonelypsp/stateful/generic_parser.py
lonelypsp/stateful/message.py
lonelypsp/stateful/parser.py
lonelypsp/stateful/parser_helpers.py
lonelypsp/stateful/serializer_helpers.py
lonelypsp/stateful/messages/configure.py
lonelypsp/stateful/messages/confirm_configure.py
lonelypsp/stateful/messages/confirm_notify.py
lonelypsp/stateful/messages/confirm_receive.py
lonelypsp/stateful/messages/confirm_subscribe.py
lonelypsp/stateful/messages/confirm_unsubscribe.py
lonelypsp/stateful/messages/continue_notify.py
lonelypsp/stateful/messages/continue_receive.py
lonelypsp/stateful/messages/disable_zstd_custom.py
lonelypsp/stateful/messages/enable_zstd_custom.py
lonelypsp/stateful/messages/enable_zstd_preset.py
lonelypsp/stateful/messages/missed.py
lonelypsp/stateful/messages/notify.py
lonelypsp/stateful/messages/notify_stream.py
lonelypsp/stateful/messages/receive_stream.py
lonelypsp/stateful/messages/subscribe.py
lonelypsp/stateful/messages/unsubscribe.py
lonelypsp/stateless/constants.py
lonelypsp/stateless/make_strong_etag.py
lonelypsp/tracing/README.md
lonelypsp/tracing/root.py
lonelypsp/tracing/impl/noop/shared/handle_trusted_notify.py
lonelypsp/tracing/impl/simple/README.md
lonelypsp/tracing/impl/simple/config.py
lonelypsp/tracing/impl/simple/db.py
lonelypsp/tracing/impl/simple/root.py
lonelypsp/tracing/impl/simple/frontend/router.py
lonelypsp/tracing/impl/simple/migrations/0001_stateless_notify.sql
lonelypsp/tracing/impl/simple/shared/cristians.py
lonelypsp/tracing/impl/simple/stateless/notify.py
lonelypsp/tracing/impl/simple/stateless/root.py
lonelypsp/tracing/shared/handle_trusted_notify.py
lonelypsp/tracing/shared/tracing_and_followup.py
lonelypsp/tracing/stateless/notify.py
lonelypsp-0.0.47.dist-info/licenses/LICENSE.md
lonelypsp-0.0.47.dist-info/METADATA
lonelypsp-0.0.47.dist-info/WHEEL
lonelypsp-0.0.47.dist-info/top_level.txt
lonelypsp-0.0.47.dist-info/RECORD
